README.rst
setup.py
picklable_itertools/__init__.py
picklable_itertools/base.py
picklable_itertools/extras.py
picklable_itertools/filter.py
picklable_itertools/grouping.py
picklable_itertools/iter_dispatch.py
picklable_itertools/map_zip.py
picklable_itertools/permutations.py
picklable_itertools/product.py
picklable_itertools/range.py
picklable_itertools/simple.py
picklable_itertools/slicing.py
picklable_itertools/tee.py
picklable_itertools.egg-info/PKG-INFO
picklable_itertools.egg-info/SOURCES.txt
picklable_itertools.egg-info/dependency_links.txt
picklable_itertools.egg-info/requires.txt
picklable_itertools.egg-info/top_level.txt
picklable_itertools.egg-info/zip-safe