Metadata-Version: 1.1
Name: picklable-itertools
Version: 0.1.1
Summary: itertools. But picklable. Even on Python 2.
Home-page: https://github.com/mila-udem/picklable-itertools
Author: David Warde-Farley
Author-email: d.warde.farley@gmail.com
License: MIT
Keywords: pickle serialize pickling itertools iterable iteration
Platform: UNKNOWN
Classifier: Development Status :: 3 - Alpha
Classifier: Intended Audience :: Developers
Classifier: Topic :: Utilities
Classifier: License :: OSI Approved :: MIT License
Classifier: Programming Language :: Python :: 2
Classifier: Programming Language :: Python :: 2.7
Classifier: Programming Language :: Python :: 3
Classifier: Programming Language :: Python :: 3.4
